amipwned/__init__.py
amipwned/amipwned.py
amipwned/config.py
amipwned/daemon.py
amipwned/database.py
amipwned/web_service.py
amipwned-0.2.0.dist-info/entry_points.txt
amipwned-0.2.0.dist-info/WHEEL
amipwned-0.2.0.dist-info/METADATA
amipwned-0.2.0.dist-info/RECORD
